{
  "title": "Feature Flags",
  "panels": [
    {
      "type": "graph",
      "title": "Flag evaluations",
      "targets": [
        { "expr": "sum by (key,variant)(rate(flag_evaluations_total[5m]))" }
      ],
      "id": 1
    },
    {
      "type": "stat",
      "title": "Evaluation errors",
      "targets": [
        { "expr": "sum(rate(flag_errors_total[5m]))" }
      ],
      "id": 2
    },
    {
      "type": "table",
      "title": "Rollout percent",
      "targets": [
        { "expr": "flag_rollout_percent" }
      ],
      "id": 3
    }
  ],
  "schemaVersion": 39,
  "version": 1
}
