{
  "records": [
    {
      "id": "rec-001",
      "geo": "US",
      "consented_partners": ["partner-a", "partner-b"],
      "consent_tags": ["analytics", "email"],
      "attributes": {
        "age": 34,
        "interests": ["security", "compliance"],
        "lifecycle_stage": "customer"
      },
      "metadata": {
        "source": "crm",
        "ingested_at": "2025-01-15T12:00:00Z"
      }
    },
    {
      "id": "rec-002",
      "geo": "CA",
      "consented_partners": ["partner-a"],
      "consent_tags": ["analytics"],
      "attributes": {
        "age": 29,
        "interests": ["threat-intel"],
        "lifecycle_stage": "prospect"
      },
      "metadata": {
        "source": "events",
        "ingested_at": "2025-01-18T09:30:00Z"
      }
    },
    {
      "id": "rec-003",
      "geo": "US",
      "consented_partners": ["partner-b"],
      "consent_tags": ["analytics", "email"],
      "attributes": {
        "age": 41,
        "interests": ["counter-intel"],
        "lifecycle_stage": "customer"
      },
      "metadata": {
        "source": "crm",
        "ingested_at": "2025-01-20T07:45:00Z"
      }
    },
    {
      "id": "rec-004",
      "geo": "FR",
      "consented_partners": ["partner-a"],
      "consent_tags": ["research"],
      "attributes": {
        "age": 37,
        "interests": ["policy"],
        "lifecycle_stage": "customer"
      },
      "metadata": {
        "source": "survey",
        "ingested_at": "2025-01-19T14:15:00Z"
      }
    },
    {
      "id": "rec-005",
      "geo": "US",
      "consented_partners": ["partner-a"],
      "consent_tags": ["analytics", "research"],
      "attributes": {
        "age": 45,
        "interests": ["risk", "operations"],
        "lifecycle_stage": "customer"
      },
      "metadata": {
        "source": "crm",
        "ingested_at": "2025-01-22T16:20:00Z"
      }
    },
    {
      "id": "rec-006",
      "geo": "BR",
      "consented_partners": ["partner-a"],
      "consent_tags": ["analytics"],
      "attributes": {
        "age": 32,
        "interests": ["field-ops"],
        "lifecycle_stage": "pilot"
      },
      "metadata": {
        "source": "field",
        "ingested_at": "2025-01-24T10:05:00Z"
      }
    }
  ]
}
