[
  {"number":20070,"title":"feat: Add CI workflow with affected-packages detection","updatedAt":"2026-03-11T10:37:42Z","url":"https://github.com/BrianCLong/summit/pull/20070"},
  {"number":20069,"title":"Add regression test suite for known issues in GraphRAG and API Gateway","updatedAt":"2026-03-11T10:34:32Z","url":"https://github.com/BrianCLong/summit/pull/20069"},
  {"number":20068,"title":"ci: add automated PR hygiene workflows","updatedAt":"2026-03-11T10:31:57Z","url":"https://github.com/BrianCLong/summit/pull/20068"},
  {"number":20067,"title":"feat: add performance and latency benchmark suite for GraphRAG","updatedAt":"2026-03-11T10:30:13Z","url":"https://github.com/BrianCLong/summit/pull/20067"},
  {"number":20066,"title":"docs: add data model and schema documentation","updatedAt":"2026-03-11T10:29:36Z","url":"https://github.com/BrianCLong/summit/pull/20066"},
  {"number":20065,"title":"Add local observability stack (Prometheus + Grafana + Loki)","updatedAt":"2026-03-11T10:16:00Z","url":"https://github.com/BrianCLong/summit/pull/20065"},
  {"number":20064,"title":"Add Ingestion Pipeline Evaluation Harness","updatedAt":"2026-03-11T10:14:31Z","url":"https://github.com/BrianCLong/summit/pull/20064"},
  {"number":20063,"title":"chore(ci): Setup automated dependency updates","updatedAt":"2026-03-11T10:13:47Z","url":"https://github.com/BrianCLong/summit/pull/20063"},
  {"number":20062,"title":"Consolidate and Update Summit API Reference Documentation","updatedAt":"2026-03-11T10:10:32Z","url":"https://github.com/BrianCLong/summit/pull/20062"},
  {"number":20061,"title":"feat(evals): build knowledge graph evaluation harness","updatedAt":"2026-03-11T10:10:06Z","url":"https://github.com/BrianCLong/summit/pull/20061"},
  {"number":20060,"title":"docs: implement comprehensive security model and threat documentation","updatedAt":"2026-03-11T10:09:12Z","url":"https://github.com/BrianCLong/summit/pull/20060"},
  {"number":20059,"title":"Add automated release workflow and CI validation","updatedAt":"2026-03-11T10:09:13Z","url":"https://github.com/BrianCLong/summit/pull/20059"},
  {"number":20058,"title":"feat(docs): add weekly agent ecosystem report and evaluation insights","updatedAt":"2026-03-11T09:58:33Z","url":"https://github.com/BrianCLong/summit/pull/20058"},
  {"number":20057,"title":"feat: implement comprehensive summit monitoring and observability","updatedAt":"2026-03-11T09:54:59Z","url":"https://github.com/BrianCLong/summit/pull/20057"},
  {"number":20056,"title":"feat(leaderboard): publish result bundles","updatedAt":"2026-03-11T09:53:53Z","url":"https://github.com/BrianCLong/summit/pull/20056"},
  {"number":20055,"title":"feat(bench): benchmark expansion","updatedAt":"2026-03-11T09:53:28Z","url":"https://github.com/BrianCLong/summit/pull/20055"},
  {"number":20054,"title":"feat(orchestration): implement scheduled Jules supervisor","updatedAt":"2026-03-11T09:52:19Z","url":"https://github.com/BrianCLong/summit/pull/20054"},
  {"number":20053,"title":"feat: implement scheduled repo health monitoring and daily benchmarks","updatedAt":"2026-03-11T09:48:06Z","url":"https://github.com/BrianCLong/summit/pull/20053"},
  {"number":20052,"title":"feat(adapters): external framework support","updatedAt":"2026-03-11T09:45:00Z","url":"https://github.com/BrianCLong/summit/pull/20052"},
  {"number":20051,"title":"docs: Add comprehensive governance and contribution specification","updatedAt":"2026-03-11T09:44:58Z","url":"https://github.com/BrianCLong/summit/pull/20051"}
]
