{
  "issue_number": 12863,
  "title": "feat: R1 Rapid Attribution Plan & Backlog",
  "url": "https://github.com/BrianCLong/summit/pull/12863",
  "state": "closed",
  "labels": [],
  "updatedAt": "2025-12-17T21:55:56Z",
  "createdAt": "2025-11-29T07:04:29Z",
  "classification": "unknown",
  "solved_status": "not_solved",
  "evidence": {
    "prs": [],
    "commits": [],
    "paths": [],
    "tests": []
  },
  "actions_taken": [],
  "verification": [],
  "notes": "",
  "run_id": "d1bc04ce-0157-48fe-b52e-2a1c4d85379b"
}