{
  "issue_number": 637,
  "title": "chore(deps): bump dlib from 19.24.2 to 20.0.0",
  "url": "https://github.com/BrianCLong/summit/pull/637",
  "state": "closed",
  "labels": [
    {
      "id": 9102204143,
      "node_id": "LA_kwDOPaNncM8AAAACHoic7w",
      "url": "https://api.github.com/repos/BrianCLong/summit/labels/dependencies",
      "name": "dependencies",
      "color": "0366d6",
      "default": false,
      "description": "Pull requests that update a dependency file"
    },
    {
      "id": 9133974250,
      "node_id": "LA_kwDOPaNncM8AAAACIG1i6g",
      "url": "https://api.github.com/repos/BrianCLong/summit/labels/python",
      "name": "python",
      "color": "2b67c6",
      "default": false,
      "description": "Pull requests that update python code"
    }
  ],
  "updatedAt": "2025-08-19T14:22:03Z",
  "createdAt": "2025-08-19T09:39:30Z",
  "classification": "unknown",
  "solved_status": "already_solved",
  "evidence": {
    "prs": [
      {
        "number": 15134,
        "url": "https://github.com/BrianCLong/summit/pull/15134",
        "mergedAt": null,
        "title": "chore(deps): bump actions/github-script from 7 to 8"
      },
      {
        "number": 11926,
        "url": "https://github.com/BrianCLong/summit/pull/11926",
        "mergedAt": "2025-11-20T10:20:02Z",
        "title": "Build natural language to graph query translator"
      },
      {
        "number": 12296,
        "url": "https://github.com/BrianCLong/summit/pull/12296",
        "mergedAt": "2025-11-25T20:34:22Z",
        "title": "Bump body-parser from 2.2.0 to 2.2.1 in /conductor-ui/backend"
      },
      {
        "number": 11233,
        "url": "https://github.com/BrianCLong/summit/pull/11233",
        "mergedAt": "2025-10-16T16:05:19Z",
        "title": "fix/msw vector adapter typings"
      },
      {
        "number": 615,
        "url": "https://github.com/BrianCLong/summit/pull/615",
        "mergedAt": "2025-08-18T14:31:47Z",
        "title": "chore(deps): bump web-vitals from 3.5.2 to 5.1.0 in /client"
      },
      {
        "number": 613,
        "url": "https://github.com/BrianCLong/summit/pull/613",
        "mergedAt": "2025-08-18T14:25:09Z",
        "title": "chore(deps-dev): bump @testing-library/jest-dom from 5.17.0 to 6.7.0 in /client"
      }
    ],
    "commits": [],
    "paths": [],
    "tests": []
  },
  "actions_taken": [],
  "verification": [],
  "notes": "",
  "run_id": "e3bea500-47da-4d74-a8d4-c5f5ce191303"
}
