{
  "issue_number": 933,
  "title": "Integration Rollup: absorb backlog into main",
  "url": "https://github.com/BrianCLong/summit/pull/933",
  "state": "closed",
  "labels": [],
  "updatedAt": "2025-08-29T03:24:56Z",
  "createdAt": "2025-08-29T03:21:54Z",
  "classification": "unknown",
  "solved_status": "already_solved",
  "evidence": {
    "prs": [
      {
        "number": 15133,
        "url": "https://github.com/BrianCLong/summit/pull/15133",
        "mergedAt": null,
        "title": "chore(deps): bump aws-actions/configure-aws-credentials from 4 to 5"
      },
      {
        "number": 1266,
        "url": "https://github.com/BrianCLong/summit/pull/1266",
        "mergedAt": "2025-09-16T22:05:41Z",
        "title": "chore(ci): finalization kit + protections"
      }
    ],
    "commits": [],
    "paths": [],
    "tests": []
  },
  "actions_taken": [],
  "verification": [],
  "notes": "",
  "run_id": "e3bea500-47da-4d74-a8d4-c5f5ce191303"
}
