{
  "$schema": "http://json-schema.org/draft-07/schema#",
  "title": "InvestigationRun",
  "description": "An immutable, replayable record of an investigation workflow execution.",
  "type": "object",
  "properties": {
    "run_id": {
      "type": "string",
      "description": "A unique, deterministic identifier for this run."
    },
    "inputs": {
      "type": "object",
      "description": "The exact inputs provided to the investigation.",
      "additionalProperties": true
    },
    "scope": {
      "type": "object",
      "description": "The defined scope or boundaries of the investigation.",
      "additionalProperties": true
    },
    "tools_invoked": {
      "type": "array",
      "description": "A deterministically ordered list of tools invoked during the run.",
      "items": {
        "type": "object",
        "properties": {
          "tool_id": {
            "type": "string"
          },
          "version": {
            "type": "string"
          },
          "input_hash": {
            "type": "string"
          },
          "output_hash": {
            "type": "string"
          }
        },
        "required": ["tool_id", "version", "input_hash", "output_hash"],
        "additionalProperties": false
      }
    },
    "outputs_summary": {
      "type": "object",
      "description": "A summary of the outputs generated by the investigation.",
      "additionalProperties": true
    }
  },
  "required": ["run_id", "inputs", "scope", "tools_invoked", "outputs_summary"],
  "additionalProperties": false
}