[
  {
    "feature": "Accessibility + Keyboard Gate",
    "tier": "A",
    "artifact": "e2e/a11y-keyboard/a11y-gate.spec.ts",
    "ciStatus": "wired",
    "evidence": ["reports/a11y-keyboard/README.md", ".github/workflows/a11y-keyboard-smoke.yml"],
    "keywords": ["accessibility", "keyboard"],
    "notes": "Blocks GA on serious/critical axe findings or keyboard navigation regressions; artifact upload required."
  },
  {
    "feature": "Demo Mode Hard Gate",
    "tier": "B",
    "artifact": "testing/ga-verification/ga-features.ga.test.mjs",
    "ciStatus": "wired",
    "evidence": ["scripts/demo-up.sh", "docs/archive/README-UPDATED.md"],
    "keywords": ["DEMO_MODE", "Demo Mode"],
    "notes": "Demo mode must remain behind explicit gate; verification is node-native to avoid Jest instability."
  },
  {
    "feature": "Rate Limiting",
    "tier": "B",
    "artifact": "testing/ga-verification/ga-features.ga.test.mjs",
    "ciStatus": "wired",
    "evidence": ["docs/API_RATE_LIMITING.md"],
    "keyword": "rate limiting",
    "notes": "Documentation-driven contract while runtime harness is stabilized."
  },
  {
    "feature": "AuthN/AuthZ Helpers",
    "tier": "B",
    "artifact": "testing/ga-verification/ga-features.ga.test.mjs",
    "ciStatus": "wired",
    "evidence": ["docs/AUTHZ_IMPLEMENTATION_SUMMARY.md"],
    "keyword": "Authorization",
    "notes": "Ensures helper guidance is anchored to the audited AuthZ summary."
  },
  {
    "feature": "Observability Taxonomy",
    "tier": "B",
    "artifact": "testing/ga-verification/ga-features.ga.test.mjs",
    "ciStatus": "wired",
    "evidence": [
      "summit_observability/METRICS.md",
      "summit_observability/LOGS.md",
      "summit_observability/EVENTS.md"
    ],
    "keywords": ["metrics", "logs", "events"],
    "notes": "Keeps the metrics/logs/events taxonomy intact."
  },
  {
    "feature": "Data Classification & Governance",
    "tier": "B",
    "artifact": "testing/ga-verification/ga-features.ga.test.mjs",
    "ciStatus": "wired",
    "evidence": ["docs/DATA_GOVERNANCE.md"],
    "keyword": "Governance",
    "notes": "Guards the canonical governance document."
  },
  {
    "feature": "Policy Preflight & Receipts",
    "tier": "C",
    "artifact": "scripts/ga/verify-ga-surface.mjs",
    "ciStatus": "wired",
    "evidence": ["PROVENANCE_SCHEMA.md"],
    "keyword": "provenance",
    "notes": "Validated via schema checks to avoid test runner dependency."
  },
  {
    "feature": "Ingestion Security Hardening",
    "tier": "B",
    "artifact": "testing/ga-verification/ga-features.ga.test.mjs",
    "ciStatus": "wired",
    "evidence": ["docs/security/security-architecture-and-policies.md"],
    "keyword": "ingestion",
    "notes": "Ensures ingestion hardening expectations stay documented."
  },
  {
    "feature": "Evidence Map Completeness",
    "tier": "B",
    "artifact": "scripts/ci/verify_evidence_map.mjs",
    "ciStatus": "wired",
    "evidence": ["docs/ga/evidence_map.yml"],
    "keyword": "evidence",
    "notes": "Blocks GA when evidence claims lack paths, verification commands, or indicators."
  },
  {
    "feature": "Security Ledger Gate",
    "tier": "B",
    "artifact": "scripts/ci/verify_security_ledger.mjs",
    "ciStatus": "wired",
    "evidence": ["docs/security/security_ledger.yml"],
    "keyword": "security ledger",
    "notes": "Blocks GA on open high/critical security items."
  },
  {
    "feature": "Repo Hygiene Gate",
    "tier": "C",
    "artifact": "scripts/ci/check_repo_hygiene.sh",
    "ciStatus": "wired",
    "evidence": ["config/forbidden-files.txt"],
    "keyword": "hygiene",
    "notes": "Ensures no untracked or forbidden files reach GA validation."
  },
  {
    "feature": "Logging Safety Gate",
    "tier": "C",
    "artifact": "scripts/ci/check_logging_safety.mjs",
    "ciStatus": "wired",
    "evidence": ["scripts/ci/console-log-scan.cjs"],
    "keyword": "logging",
    "notes": "Prevent console logging regressions in GA paths."
  },
  {
    "feature": "Extension Governance Gate",
    "tier": "C",
    "artifact": "scripts/ci/check_extensions_compliance.mjs",
    "ciStatus": "wired",
    "evidence": ["extensions/package.json"],
    "keyword": "extensions",
    "notes": "Ensures extension metadata is complete and discoverable."
  },
  {
    "feature": "Integrity Budgets Gate",
    "tier": "C",
    "artifact": "scripts/ci/check_integrity_budgets.mjs",
    "ciStatus": "wired",
    "evidence": ["performance-budgets.json"],
    "keyword": "budgets",
    "notes": "Validates performance budget baselines remain populated."
  },
  {
    "feature": "Trust Dashboard Gate",
    "tier": "C",
    "artifact": "scripts/ops/generate_trust_dashboard.mjs",
    "ciStatus": "wired",
    "evidence": ["docs/ops/TRUST_DASHBOARD.md"],
    "keyword": "trust dashboard",
    "notes": "Aggregates GA hard-gate results into a single report."
  }
]
